{
    "meta": {
        "question_number": 650,
        "subjects": "Annual Ground Water Quality Report, 2024",
        "loksabha_number": "18",
        "member": [
            "Shri Bhartruhari Mahtab",
            "Shri P C Mohan",
            "Shri Tapir Gao",
            "Dr. Hemant Vishnu Savara",
            "Dr. Vinod Kumar Bind",
            "Dr. Rajesh Mishra",
            "Shri Praveen Patel",
            "Shri Vishweshwar Hegde Kageri",
            "Shri Yogender Chandolia",
            "Shri Lumbaram Choudhary",
            "Shri P P Chaudhary",
            "Shri Pratap Chandra Sarangi",
            "Shri Jaswantsinh Sumanbhai Bhabhor",
            "Shri Khagen Murmu",
            "Shri Mahesh Kashyap",
            "Smt. Smita Uday Wagh",
            "Dr. Bhola Singh",
            "Shri Dineshbhai Makwana",
            "Shri Tejasvi Surya"
        ],
        "ministry": "JAL SHAKTI",
        "type": "UNSTARRED",
        "date": "06.02.2025",
        "questions_file_path_local": "sansad/18/iv/ministries/jal-shakti/650/AU650_5ouwII.pdf",
        "questions_file_path_web": "https://sansad.in/getFile/loksabhaquestions/annex/184/AU650_5ouwII.pdf?source=pqals",
        "questions_file_path_hindi_local": null,
        "questions_file_path_hindi_web": "https://sansad.in/getFile/loksabhaquestions/qhindi/184/AU650_5ouwII.pdf?source=pqals",
        "question_text": null,
        "answer_text": null,
        "session_number": "4"
    }
}