{
    "meta": {
        "question_number": 1852,
        "subjects": "Status of Pan-India Emergency Alert System",
        "loksabha_number": "18",
        "member": [
            "Ms Iqra Choudhary"
        ],
        "ministry": "HOME AFFAIRS",
        "type": "UNSTARRED",
        "date": "11.03.2025",
        "questions_file_path_local": "sansad/18/iv/ministries/home-affairs/1852/AU1852_e9cBNL.pdf",
        "questions_file_path_web": "https://sansad.in/getFile/loksabhaquestions/annex/184/AU1852_e9cBNL.pdf?source=pqals",
        "questions_file_path_hindi_local": null,
        "questions_file_path_hindi_web": "https://sansad.in/getFile/loksabhaquestions/qhindi/184/AU1852_e9cBNL.pdf?source=pqals",
        "question_text": null,
        "answer_text": null,
        "session_number": "4"
    }
}