{
    "meta": {
        "question_number": 3888,
        "subjects": "Education Hub within Central Universities",
        "loksabha_number": "18",
        "member": [
            "Shri Dharambir Singh"
        ],
        "ministry": "EDUCATION",
        "type": "UNSTARRED",
        "date": "24.03.2025",
        "questions_file_path_local": "sansad/18/iv/ministries/education/3888/AU3888_72LDdZ.pdf",
        "questions_file_path_web": "https://sansad.in/getFile/loksabhaquestions/annex/184/AU3888_72LDdZ.pdf?source=pqals",
        "questions_file_path_hindi_local": null,
        "questions_file_path_hindi_web": "https://sansad.in/getFile/loksabhaquestions/qhindi/184/AU3888_72LDdZ.pdf?source=pqals",
        "question_text": null,
        "answer_text": null,
        "session_number": "4"
    }
}