{
    "meta": {
        "question_number": 2082,
        "subjects": "Support for NESAC Projects",
        "loksabha_number": "18",
        "member": [
            "Shri Yogender Chandolia",
            "Shri Anurag Sharma",
            "Shri Praveen Patel",
            "Shri Tapir Gao"
        ],
        "ministry": "SPACE",
        "type": "UNSTARRED",
        "date": "12.03.2025",
        "questions_file_path_local": "sansad/18/iv/ministries/space/2082/AU2082_yCme8Q.pdf",
        "questions_file_path_web": "https://sansad.in/getFile/loksabhaquestions/annex/184/AU2082_yCme8Q.pdf?source=pqals",
        "questions_file_path_hindi_local": null,
        "questions_file_path_hindi_web": "https://sansad.in/getFile/loksabhaquestions/qhindi/184/AU2082_yCme8Q.pdf?source=pqals",
        "question_text": null,
        "answer_text": null,
        "session_number": "4"
    }
}