{
    "meta": {
        "question_number": 981,
        "subjects": "India State of Forest Report, 2023",
        "loksabha_number": "18",
        "member": [
            "Shri Prabhakar Reddy Vemireddy"
        ],
        "ministry": "ENVIRONMENT, FOREST AND CLIMATE CHANGE",
        "type": "UNSTARRED",
        "date": "10.02.2025",
        "questions_file_path_local": "sansad/18/iv/ministries/environment-forest-and-climate-change/981/AU981_zFFugf.pdf",
        "questions_file_path_web": "https://sansad.in/getFile/loksabhaquestions/annex/184/AU981_zFFugf.pdf?source=pqals",
        "questions_file_path_hindi_local": null,
        "questions_file_path_hindi_web": "https://sansad.in/getFile/loksabhaquestions/qhindi/184/AU981_zFFugf.pdf?source=pqals",
        "question_text": null,
        "answer_text": null,
        "session_number": "4"
    }
}