{
    "meta": {
        "question_number": 3852,
        "subjects": "Impact of depreciation of Rupee on Inflation and Essential Imports",
        "loksabha_number": "18",
        "member": [
            "Shri Kalyan Banerjee"
        ],
        "ministry": "FINANCE",
        "type": "UNSTARRED",
        "date": "24.03.2025",
        "questions_file_path_local": "sansad/18/iv/ministries/finance/3852/AU3852_yV90pz.pdf",
        "questions_file_path_web": "https://sansad.in/getFile/loksabhaquestions/annex/184/AU3852_yV90pz.pdf?source=pqals",
        "questions_file_path_hindi_local": null,
        "questions_file_path_hindi_web": "https://sansad.in/getFile/loksabhaquestions/qhindi/184/AU3852_yV90pz.pdf?source=pqals",
        "question_text": null,
        "answer_text": null,
        "session_number": "4"
    }
}