{
    "meta": {
        "question_number": 3359,
        "subjects": "Tribal Research Institutes in Maharashtra",
        "loksabha_number": "18",
        "member": [
            "Shri Shyamkumar Daulat Barve"
        ],
        "ministry": "TRIBAL AFFAIRS",
        "type": "UNSTARRED",
        "date": "20.03.2025",
        "questions_file_path_local": "sansad/18/iv/ministries/tribal-affairs/3359/AU3359_Ir2bbg.pdf",
        "questions_file_path_web": "https://sansad.in/getFile/loksabhaquestions/annex/184/AU3359_Ir2bbg.pdf?source=pqals",
        "questions_file_path_hindi_local": null,
        "questions_file_path_hindi_web": "https://sansad.in/getFile/loksabhaquestions/qhindi/184/AU3359_Ir2bbg.pdf?source=pqals",
        "question_text": null,
        "answer_text": null,
        "session_number": "4"
    }
}