{
    "meta": {
        "question_number": 3263,
        "subjects": "Formalization of MSMEs",
        "loksabha_number": "18",
        "member": [
            "Shri Vishaldada Prakashbapu Patil"
        ],
        "ministry": "MICRO, SMALL AND MEDIUM ENTERPRISES",
        "type": "UNSTARRED",
        "date": "20.03.2025",
        "questions_file_path_local": "sansad/18/iv/ministries/micro-small-and-medium-enterprises/3263/AU3263_LHoxnP.pdf",
        "questions_file_path_web": "https://sansad.in/getFile/loksabhaquestions/annex/184/AU3263_LHoxnP.pdf?source=pqals",
        "questions_file_path_hindi_local": null,
        "questions_file_path_hindi_web": "https://sansad.in/getFile/loksabhaquestions/qhindi/184/AU3263_LHoxnP.pdf?source=pqals",
        "question_text": null,
        "answer_text": null,
        "session_number": "4"
    }
}