{
    "meta": {
        "question_number": 3097,
        "subjects": "Child Sexual Abuse Material Laws",
        "loksabha_number": "18",
        "member": [
            "Dr. Nishikant Dubey",
            "Smt. Smita Uday Wagh"
        ],
        "ministry": "ELECTRONICS AND INFORMATION TECHNOLOGY",
        "type": "UNSTARRED",
        "date": "19.03.2025",
        "questions_file_path_local": "sansad/18/iv/ministries/electronics-and-information-technology/3097/AU3097_Hra2wU.pdf",
        "questions_file_path_web": "https://sansad.in/getFile/loksabhaquestions/annex/184/AU3097_Hra2wU.pdf?source=pqals",
        "questions_file_path_hindi_local": null,
        "questions_file_path_hindi_web": "https://sansad.in/getFile/loksabhaquestions/qhindi/184/AU3097_Hra2wU.pdf?source=pqals",
        "question_text": null,
        "answer_text": null,
        "session_number": "4"
    }
}