{
    "meta": {
        "question_number": 3628,
        "subjects": "Multi-Drug Resistant Tuberculosis",
        "loksabha_number": "18",
        "member": [
            "Shri Arun Govil",
            "Shri Balabhadra Majhi",
            "Smt. Kamaljeet Sehrawat",
            "Shri Manoj Tiwari",
            "Shri Dineshbhai Makwana",
            "Shri Kanwar Singh Tanwar",
            "Smt. Bharti Pardhi",
            "Shri Chavda Vinod Lakhamshi",
            "Shri Tapir Gao",
            "Shri Shankar Lalwani",
            "Shri Gajendra  Singh Patel",
            "Dr. Rajesh Mishra",
            "Smt. Kamlesh Jangde",
            "Shri Praveen Patel",
            "Shri Yogender Chandolia",
            "Shri Rajkumar Chahar",
            "Shri Jai Prakash",
            "Shri Bidyut Baran Mahato",
            "Dr. K Sudhakar",
            "Shri Bhojraj Nag",
            "Dr. Hemant Vishnu Savara",
            "Shri Dharambir Singh",
            "Shri Naba Charan Majhi",
            "Shri Pradeep Kumar Singh",
            "Shri Shrirang Appa Chandu Barne",
            "Shri Dilip Saikia",
            "Smt. Mahima Kumari Mewar",
            "Shri Trivendra Singh Rawat",
            "Shri P P Chaudhary",
            "Shri Lumbaram Choudhary",
            "Shri Janardan Mishra",
            "Shri Jaswantsinh Sumanbhai Bhabhor",
            "Shri Suresh Kumar Kashyap",
            "Shri Captain Brijesh Chowta"
        ],
        "ministry": "HEALTH AND FAMILY WELFARE",
        "type": "UNSTARRED",
        "date": "21.03.2025",
        "questions_file_path_local": "sansad/18/iv/ministries/health-and-family-welfare/3628/AU3628_zgI0ou.pdf",
        "questions_file_path_web": "https://sansad.in/getFile/loksabhaquestions/annex/184/AU3628_zgI0ou.pdf?source=pqals",
        "questions_file_path_hindi_local": null,
        "questions_file_path_hindi_web": "https://sansad.in/getFile/loksabhaquestions/qhindi/184/AU3628_zgI0ou.pdf?source=pqals",
        "question_text": null,
        "answer_text": null,
        "session_number": "4"
    }
}