{
    "meta": {
        "question_number": 2930,
        "subjects": "Grameen Credit Score",
        "loksabha_number": "18",
        "member": [
            "Dr. Kalanidhi Veeraswamy"
        ],
        "ministry": "RURAL DEVELOPMENT",
        "type": "UNSTARRED",
        "date": "18.03.2025",
        "questions_file_path_local": "sansad/18/iv/ministries/rural-development/2930/AU2930_NBNcyz.pdf",
        "questions_file_path_web": "https://sansad.in/getFile/loksabhaquestions/annex/184/AU2930_NBNcyz.pdf?source=pqals",
        "questions_file_path_hindi_local": null,
        "questions_file_path_hindi_web": "https://sansad.in/getFile/loksabhaquestions/qhindi/184/AU2930_NBNcyz.pdf?source=pqals",
        "question_text": null,
        "answer_text": null,
        "session_number": "4"
    }
}