{
    "meta": {
        "question_number": 2590,
        "subjects": "Integrate Technology with Education",
        "loksabha_number": "18",
        "member": [
            "Dr. Shashi Tharoor"
        ],
        "ministry": "EDUCATION",
        "type": "UNSTARRED",
        "date": "17.03.2025",
        "questions_file_path_local": "sansad/18/iv/ministries/education/2590/AU2590_0uDGND.pdf",
        "questions_file_path_web": "https://sansad.in/getFile/loksabhaquestions/annex/184/AU2590_0uDGND.pdf?source=pqals",
        "questions_file_path_hindi_local": null,
        "questions_file_path_hindi_web": "https://sansad.in/getFile/loksabhaquestions/qhindi/184/AU2590_0uDGND.pdf?source=pqals",
        "question_text": null,
        "answer_text": null,
        "session_number": "4"
    }
}